{
  "assets": [
    {
      "id": "47158934-82df-43ac-8a24-000000000001",
      "performance": {
        "total": {
          "annualizedTwr": 0.0163,
          "capitalChange": 6,
          "profitChange": 3.5,
          "valueChange": 9.5
        },
        "1M": {
          "annualizedTwr": -0.057,
          "capitalChange": 0,
          "profitChange": -0.5,
          "valueChange": -0.5
        },
        "1Y": {
          "annualizedTwr": -0.0722,
          "capitalChange": 6,
          "profitChange": -7.5,
          "valueChange": -1.5
        },
        "3Y": {
          "annualizedTwr": 0.0163,
          "capitalChange": 6,
          "profitChange": 3.5,
          "valueChange": 9.5
        }
      }
    },
    {
      "id": "47158934-82df-43ac-8a24-000000000002",
      "performance": {
        "total": {
          "annualizedTwr": 0.1382,
          "capitalChange": -5,
          "profitChange": 19,
          "valueChange": 14
        },
        "1M": {
          "annualizedTwr": 0.7832,
          "capitalChange": -5,
          "profitChange": 6,
          "valueChange": 1
        },
        "1Y": {
          "annualizedTwr": 0.1538,
          "capitalChange": -5,
          "profitChange": 17,
          "valueChange": 12
        },
        "3Y": {
          "annualizedTwr": 0.1382,
          "capitalChange": -5,
          "profitChange": 19,
          "valueChange": 14
        }
      }
    },
    {
      "id": "47158934-82df-43ac-8a24-000000000003",
      "performance": {
        "total": {
          "annualizedTwr": 0.0839,
          "capitalChange": 0,
          "profitChange": 9,
          "valueChange": 9
        },
        "1M": {
          "annualizedTwr": 0.7014,
          "capitalChange": -5,
          "profitChange": 6,
          "valueChange": 1
        },
        "1Y": {
          "annualizedTwr": 0.0839,
          "capitalChange": 0,
          "profitChange": 9,
          "valueChange": 9
        },
        "3Y": {
          "annualizedTwr": 0.0839,
          "capitalChange": 0,
          "profitChange": 9,
          "valueChange": 9
        }
      }
    },
    {
      "id": "47158934-82df-43ac-8a24-000000000004",
      "performance": {
        "total": {
          "annualizedTwr": 0.1643,
          "capitalChange": -5,
          "profitChange": 9,
          "valueChange": 4
        },
        "1M": {
          "annualizedTwr": 0.6348,
          "capitalChange": -5,
          "profitChange": 6,
          "valueChange": 1
        },
        "1Y": {
          "annualizedTwr": 0.1643,
          "capitalChange": -5,
          "profitChange": 9,
          "valueChange": 4
        },
        "3Y": {
          "annualizedTwr": 0.1643,
          "capitalChange": -5,
          "profitChange": 9,
          "valueChange": 4
        }
      }
    }
  ],
  "portfolio": {
    "total": {
      "annualizedTwr": 0.128,
      "capitalChange": 336.0,
      "valueChange": 410.0,
      "profitChange": 74.0
    },
    "1M": {
      "annualizedTwr": 0.5111,
      "capitalChange": -15.0,
      "valueChange": 2.5,
      "profitChange": 17.5
    },
    "1Y": {
      "annualizedTwr": 0.2219,
      "capitalChange": 221.0,
      "valueChange": 288.5,
      "profitChange": 67.5
    },
    "3Y": {
      "annualizedTwr": 0.128,
      "capitalChange": 336.0,
      "valueChange": 410.0,
      "profitChange": 74.0
    }
  }
}